README.rst
setup.py
ratebeer/__init__.py
ratebeer/_version.py
ratebeer/models.py
ratebeer/ratebeer.py
ratebeer/rb_exceptions.py
ratebeer/soup.py
ratebeer.egg-info/PKG-INFO
ratebeer.egg-info/SOURCES.txt
ratebeer.egg-info/dependency_links.txt
ratebeer.egg-info/requires.txt
ratebeer.egg-info/top_level.txt