Metadata-Version: 1.1
Name: ratebeer
Version: 2.3.0
Summary: Python API for RateBeer.com
Home-page: https://github.com/alilja/ratebeer
Author: Andrew Lilja
Author-email: andrewlilja@gmail.com
License: Unlicense (a.k.a. Public Domain)
Keywords: ratebeer rate beer ratings
Platform: UNKNOWN
Classifier: Development Status :: 4 - Beta
Classifier: Intended Audience :: Developers
Classifier: Natural Language :: English
Classifier: Operating System :: OS Independent
Classifier: Programming Language :: Python :: 2
Classifier: Programming Language :: Python :: 3
Classifier: Topic :: Internet
Classifier: Topic :: Internet :: WWW/HTTP
